SysArg/__init__.py
sysarg-2.0.12.dist-info/LICENSE
sysarg-2.0.12.dist-info/METADATA
sysarg-2.0.12.dist-info/WHEEL
sysarg-2.0.12.dist-info/top_level.txt
sysarg-2.0.12.dist-info/RECORD
