Metadata-Version: 2.1
Name: sysarg
Version: 2.0.12
Summary: CLI Argument Parser
Home-page: https://github.com/kagepark/SysArg
Author: Kage Park
License: MIT
Platform: UNKNOWN
Classifier: Programming Language :: Python :: 2
Classifier: Programming Language :: Python :: 3
Classifier: License :: OSI Approved :: MIT License
Classifier: Operating System :: OS Independent
License-File: LICENSE
